phonetics/__init__.py
phonetics/metaphone.py
phonetics/nysiis.py
phonetics/soundex.py
phonetics/utils.py
phonetics/tests/__init__.py
phonetics/tests/test_metaphone.py
phonetics_py-1.0.5.dist-info/METADATA
phonetics_py-1.0.5.dist-info/WHEEL
phonetics_py-1.0.5.dist-info/top_level.txt
phonetics_py-1.0.5.dist-info/RECORD
