Metadata-Version: 2.1
Name: phonetics-py
Version: 1.0.5
Summary: Compute phonetic key of strings for indexing or fuzzy matching
Home-page: https://github.com/smirnoffs/phonetics-py
Author: Zack Dibe
Author-email: contact@zackdibe.com
License: MIT
Keywords: phonetics metaphone soundex indexing search fuzzy
Classifier: Development Status :: 3 - Alpha
Classifier: Intended Audience :: Developers
Classifier: License :: OSI Approved :: MIT License
Classifier: Natural Language :: English
Classifier: Topic :: Text Processing :: General
Classifier: Topic :: Text Processing :: Indexing
Classifier: Topic :: Text Processing :: Linguistic
Classifier: Topic :: Internet :: WWW/HTTP :: Indexing/Search
Classifier: Programming Language :: Python :: 2
Classifier: Programming Language :: Python :: 2.6
Classifier: Programming Language :: Python :: 2.7
Classifier: Programming Language :: Python :: 3
Classifier: Programming Language :: Python :: 3.3
Classifier: Programming Language :: Python :: 3.4
Classifier: Programming Language :: Python :: 3.5
